colarised/__init__.py
colarised/test.py
colarised-1.4.dist-info/METADATA
colarised-1.4.dist-info/WHEEL
colarised-1.4.dist-info/top_level.txt
colarised-1.4.dist-info/RECORD
