Metadata-Version: 2.1
Name: colarised
Version: 1.4
Summary: Bring Colorful code in python
Author-email: media-hr@gmail.com
License: Eclipse Public License 2.0
